gmpy2/__init__.pyi
gmpy2/py.typed
gmpy2_stubs-2.2.1.5.dist-info/licenses/LICENSE
gmpy2_stubs-2.2.1.5.dist-info/METADATA
gmpy2_stubs-2.2.1.5.dist-info/WHEEL
gmpy2_stubs-2.2.1.5.dist-info/top_level.txt
gmpy2_stubs-2.2.1.5.dist-info/RECORD
