Metadata-Version: 2.4
Name: gmpy2-stubs
Version: 2.2.1.5
Summary: Type stubs (PEP 561) for gmpy2 2.2.1: GMP, MPFR, and MPC support.
Author-email: David Osipov <personal@david-osipov.vision>
Maintainer-email: David Osipov <personal@david-osipov.vision>
License: MIT
Project-URL: Homepage, https://github.com/DavidOsipov/gmpy2-stubs
Project-URL: Issues, https://github.com/DavidOsipov/gmpy2-stubs/issues
Project-URL: Source, https://github.com/DavidOsipov/gmpy2-stubs
Project-URL: Changelog, https://github.com/DavidOsipov/gmpy2-stubs/blob/main/CHANGELOG.md
Project-URL: Security Policy, https://github.com/DavidOsipov/gmpy2-stubs/blob/main/SECURITY.md
Project-URL: Personal Website, https://david-osipov.vision
Project-URL: LinkedIn, https://www.linkedin.com/in/david-osipov
Project-URL: GitHub Profile, https://github.com/DavidOsipov
Project-URL: ISNI, https://isni.org/isni/000000051802960X
Project-URL: ORCID, https://orcid.org/0009-0005-2713-9242
Project-URL: Telegram, https://telegram.me/david_osipov
Project-URL: Signal, https://signal.me/#eu/d68l1UjrWlGVRzbfkVM1bvQMNqCqiae9GM86P_af8ZK2o5E5YSNKbL4MyM9y-2WH
Keywords: gmpy2,stubs,type hints,typing,mypy,pyright,static analysis
Classifier: Development Status :: 5 - Production/Stable
Classifier: Intended Audience :: Developers
Classifier: License :: OSI Approved :: MIT License
Classifier: Programming Language :: Python :: 3
Classifier: Programming Language :: Python :: 3.8
Classifier: Programming Language :: Python :: 3.9
Classifier: Programming Language :: Python :: 3.10
Classifier: Programming Language :: Python :: 3.11
Classifier: Programming Language :: Python :: 3.12
Classifier: Programming Language :: Python :: 3 :: Only
Classifier: Topic :: Software Development :: Libraries :: Python Modules
Classifier: Typing :: Stubs Only
Requires-Python: >=3.8
License-File: LICENSE
Dynamic: license-file
